lai_jupyter/__init__.py
lai_jupyter/component.py
lightning_jupyter-0.0.2.dist-info/LICENSE
lightning_jupyter-0.0.2.dist-info/METADATA
lightning_jupyter-0.0.2.dist-info/WHEEL
lightning_jupyter-0.0.2.dist-info/top_level.txt
lightning_jupyter-0.0.2.dist-info/RECORD
