Metadata-Version: 2.1
Name: lightning-jupyter
Version: 0.0.2
Summary: JupyterLab component for Lightning Applications
Home-page: https://github.com/Lightning-AI/LAI-Jupyter-Component
Author: William, Marc, Thomas, Krishna
Author-email: krishna@grid.ai
License: UNKNOWN
Platform: UNKNOWN
Requires-Python: >=3.7
License-File: LICENSE
Requires-Dist: jupyterlab
Requires-Dist: lightning
Provides-Extra: test
Requires-Dist: coverage ; extra == 'test'
Requires-Dist: codecov (>=2.1) ; extra == 'test'
Requires-Dist: pytest (>=3.0.5) ; extra == 'test'
Requires-Dist: pytest-cov ; extra == 'test'
Requires-Dist: pytest-flake8 ; extra == 'test'
Requires-Dist: flake8 ; extra == 'test'
Requires-Dist: check-manifest ; extra == 'test'
Requires-Dist: twine (==1.13.0) ; extra == 'test'
Requires-Dist: jupyterlab (==3.4.3) ; extra == 'test'
Requires-Dist: lightning ; extra == 'test'
